Traffic-Light-Controller/traffic_light.v
module traffic_light (
    input clk,
    input reset,
    output reg red,
    output reg green,
    output reg yellow
    );


// State encoding
    parameter RED_STATE = 2'b00;      // RED=00
    parameter GREEN_STATE = 2'b01;    // GREEN=01
    parameter YELLOW_STATE = 2'b10;   // YELLOW=10


    reg [1:0] state;          // a 2-bit register to store the current state.
    reg [3:0] counter;        // a 4-bit counter (counts 0-15) to track how long we r in each state.


// Sequential Logic: runs on every clock edge.

    always @(posedge clk or posedge reset) begin     // This block runs every time the clock ticks (rising edge) or when reset is pressed.
        if (reset) begin                             // If reset is pressed, then ....
            state <= RED_STATE;                      // Reset to RED state
            counter <= 0;                            // set counter to 0
        end
        else begin                                   // If reset is not pressed, then ....
            case (state)                             // Check the current state
                RED_STATE: begin                     // If we are in RED state, then ...
                    if (counter == 5) begin          // If we have been here for 6 clock cycles (0-5), then ...
                        state <= GREEN_STATE;         
                        counter <= 0;
                    end
                    else
                        counter <= counter + 1;
                end
                GREEN_STATE: begin                   // If we are in GREEN state, then ...
                    if (counter == 5) begin          // If we have been here for 6 clock cycles (0-5), then ...
                        state <= YELLOW_STATE;
                        counter <= 0;
                    end
                    else
                        counter <= counter + 1;
                end
                YELLOW_STATE: begin                   // If we are in YELLOW state, then ...
                    if (counter == 1) begin           // If we have been here for 2 clock cycles (0-1), then ...
                        state <= RED_STATE;
                        counter <= 0;
                    end
                    else
                       counter <= counter + 1;
                end
            endcase
        end
    end

// Output Logic - combinational
    always @(*) begin                              // always @(*) - combinational block, runs whenever any signal changes.
        red = 0;
        green = 0;
        yellow = 0;
        case (state)
            RED_STATE: red = 1;                     // If we are in RED state, then turn on RED light
            GREEN_STATE: green = 1;                 // If we are in GREEN state, then turn on GREEN light
            YELLOW_STATE: yellow = 1;               // If we are in YELLOW state, then turn on YELLOW light
        endcase
    end

endmodule

Traffic-Light-Controller/traffic_light_tb.v
`timescale 1ns/1ps

module traffic_light_tb;

    reg clk;
    reg reset;
    wire red;
    wire green;
    wire yellow;

// Connect testbench to main module
    traffic_light uut (                  // uut stand for "unit under test", standard naming convention for testbenches
        .clk(clk),
        .reset(reset),
        .red(red),
        .green(green),
        .yellow(yellow)
    );

    // clock generation
    initial clk = 0;
    always #5 clk = ~clk;             // every 5ns, flip the clock signal (0 to 1 to 0 to 1 ...)
                                      // This creates a clock with a period of 10ns (100MHz)
    initial begin
        // Generate waveform file for GTKWave
        $dumpfile("traffic_light.vcd");             // creates a .vcd file that GTKWave reads to show waveforms
        $dumpvars(0, traffic_light_tb);             // tells Icarus to record all signals in the testbench

        // Apply reset
        reset = 1;
        #20;

        // Release reset and run
        reset = 0;
        #200;

        $finish;

    end


    // Print signal values to terminal

    initial begin
        $monitor("Time=%0t reset=%b red=%b green=%b yellow=%b",
                $time, reset, red, green, yellow);
    end

endmodule

// $monitor automatically prints whenever any signal changes

Traffic-Light-Controller/traffic_light.vcd
$date
	Thu Jul 09 12:02:47 2026
$end
$version
	Icarus Verilog
$end
$timescale
	1ps
$end
$scope module traffic_light_tb $end
$var wire 1 ! yellow $end
$var wire 1 " red $end
$var wire 1 # green $end
$var reg 1 $ clk $end
$var reg 1 % reset $end
$scope module uut $end
$var wire 1 $ clk $end
$var wire 1 % reset $end
$var parameter 2 & GREEN_STATE $end
$var parameter 2 ' RED_STATE $end
$var parameter 2 ( YELLOW_STATE $end
$var reg 4 ) counter [3:0] $end
$var reg 1 # green $end
$var reg 1 " red $end
$var reg 2 * state [1:0] $end
$var reg 1 ! yellow $end
$upscope $end
$upscope $end
$enddefinitions $end
$comment Show the parameter values. $end
$dumpall
b10 (
b0 '
b1 &
$end
#0
$dumpvars
b0 *
b0 )
1%
0$
0#
1"
0!
$end
#5000
1$
#10000
0$
#15000
1$
#20000
0$
0%
#25000
b1 )
1$
#30000
0$
#35000
b10 )
1$
#40000
0$
#45000
b11 )
1$
#50000
0$
#55000
b100 )
1$
#60000
0$
#65000
b101 )
1$
#70000
0$
#75000
1#
0"
b0 )
b1 *
1$
#80000
0$
#85000
b1 )
1$
#90000
0$
#95000
b10 )
1$
#100000
0$
#105000
b11 )
1$
#110000
0$
#115000
b100 )
1$
#120000
0$
#125000
b101 )
1$
#130000
0$
#135000
1!
0#
b0 )
b10 *
1$
#140000
0$
#145000
b1 )
1$
#150000
0$
#155000
1"
0!
b0 )
b0 *
1$
#160000
0$
#165000
b1 )
1$
#170000
0$
#175000
b10 )
1$
#180000
0$
#185000
b11 )
1$
#190000
0$
#195000
b100 )
1$
#200000
0$
#205000
b101 )
1$
#210000
0$
#215000
1#
0"
b0 )
b1 *
1$
